list.txt
pfood/__init__.py
pfood/__main__.py
pfood/meta.py
pfood/pfood_main.py
pfood-1.0.0.dist-info/LICENSE
pfood-1.0.0.dist-info/METADATA
pfood-1.0.0.dist-info/WHEEL
pfood-1.0.0.dist-info/entry_points.txt
pfood-1.0.0.dist-info/top_level.txt
pfood-1.0.0.dist-info/RECORD
